fast_channels/__init__.py
fast_channels/exceptions.py
fast_channels/py.typed
fast_channels/type_defs.py
fast_channels/utils.py
fast_channels/consumer/__init__.py
fast_channels/consumer/base.py
fast_channels/consumer/http.py
fast_channels/consumer/websocket.py
fast_channels/layers/__init__.py
fast_channels/layers/base.py
fast_channels/layers/in_memory.py
fast_channels/layers/registry.py
fast_channels/layers/redis/__init__.py
fast_channels/layers/redis/core.py
fast_channels/layers/redis/pubsub.py
fast_channels/layers/redis/serializers.py
fast_channels/layers/redis/type_defs.py
fast_channels/layers/redis/utils.py
fast_channels/middleware/__init__.py
fast_channels/middleware/base.py
fast_channels/middleware/websocket.py
fast_channels/testing/__init__.py
fast_channels/testing/application.py
fast_channels/testing/http.py
fast_channels/testing/websocket.py
fast_channels-1.1.0.dist-info/METADATA
fast_channels-1.1.0.dist-info/WHEEL
fast_channels-1.1.0.dist-info/licenses/AUTHORS.rst
fast_channels-1.1.0.dist-info/licenses/LICENSE
fast_channels-1.1.0.dist-info/RECORD
