Metadata-Version: 2.4
Name: fast-channels
Version: 1.1.0
Summary: Fast Channels brings Django Channels–style consumers and channel layers to FastAPI and Starlette for real-time apps.
Project-URL: Documentation, https://fast-channels.readthedocs.io/
Project-URL: Homepage, https://github.com/huynguyengl99/fast-channels
Project-URL: Repository, https://github.com/huynguyengl99/fast-channels
Author-email: Huy Nguyen <ndhgl99@gmail.com>
License: MIT License
License-File: AUTHORS.rst
License-File: LICENSE
Classifier: Environment :: Web Environment
Classifier: Intended Audience :: Developers
Classifier: Intended Audience :: Information Technology
Classifier: License :: OSI Approved :: BSD License
Classifier: Operating System :: OS Independent
Classifier: Programming Language :: Python :: 3
Classifier: Programming Language :: Python :: 3 :: Only
Classifier: Programming Language :: Python :: 3.10
Classifier: Programming Language :: Python :: 3.11
Classifier: Programming Language :: Python :: 3.12
Classifier: Programming Language :: Python :: 3.13
Classifier: Topic :: Internet :: WWW/HTTP
Classifier: Topic :: Internet :: WWW/HTTP :: Dynamic Content
Classifier: Topic :: Software Development
Classifier: Topic :: Software Development :: Libraries
Classifier: Topic :: Software Development :: Libraries :: Application Frameworks
Requires-Python: <4.0,>=3.11
Requires-Dist: asgiref<4,>=3
Provides-Extra: redis
Requires-Dist: cryptography; extra == 'redis'
Requires-Dist: msgpack; extra == 'redis'
Requires-Dist: redis; extra == 'redis'
